{
  "tasks": [
    {
      "id": 2,
      "text": "Meeting at School",
      "day": "May 6th at 1:30pm",
      "reminder": true
    },
    {
      "id": 4,
      "text": "RRR Appointment",
      "day": "May 5th at 2:30pm",
      "reminder": true
    },
    {
      "id": 5,
      "text": "MMM at School",
      "day": "June 6th at 1:30pm",
      "reminder": false
    },
    {
      "id": 6,
      "text": "UUU at Club",
      "day": "Aug 10th at 10:30pm",
      "reminder": false
    },
    {
      "text": "awdw",
      "day": "qawd",
      "reminder": true,
      "id": 8
    }
  ]
}